azure_nag/__init__.py
azure_nag/azure_parser.py
azure_nag/azure_parser_interpolator.py
azure_nag/main.py
azure_nag/report_helper.py
azure_nag/models/__init__.py
azure_nag/models/azure_function.py
azure_nag/models/azure_output.py
azure_nag/models/azure_parameter.py
azure_nag/models/azure_resource.py
azure_nag/models/azure_template.py
azure_nag/models/azure_variable.py
azure_nag/models/parameter_helper.py
azure_nag/rules/__init__.py
azure_nag/rules/azure_compute_disk_rule.py
azure_nag/rules/azure_storageaccount_encrypted_rule.py
tests/rules/__init__.py
tests/rules/test_azure_compute_disk_rule.py
tests/rules/test_azure_storageaccount_encrypted_rule.py
tests/rules/custom/__init__.py
tests/rules/custom/custom_rule_for_option_testing.py
tests/rules/custom/duplicate_custom_rule_for_testing.py
azure_nag-0.0.2.dist-info/LICENSE
azure_nag-0.0.2.dist-info/METADATA
azure_nag-0.0.2.dist-info/WHEEL
azure_nag-0.0.2.dist-info/entry_points.txt
azure_nag-0.0.2.dist-info/top_level.txt
azure_nag-0.0.2.dist-info/RECORD
